{
  "timestamp": "2025-09-09T06:32:42.430325",
  "total_records": 15,
  "missing_values": {
    "by_column": {
      "date": 0,
      "city": 0,
      "state": 0,
      "lat": 0,
      "lon": 0,
      "temp_max_f": 0,
      "temp_min_f": 0,
      "temp_avg_f": 0,
      "day_of_week": 0,
      "is_weekend": 0,
      "temp_range": 0,
      "eia_region": 0,
      "energy_consumption_mwh": 0,
      "temp_change_f": 5,
      "energy_change_mwh": 5,
      "energy_change_pct": 5
    },
    "total_missing": 15,
    "percentage_missing": 100.0
  },
  "outliers": {
    "temperature": {
      "count": 0,
      "percentage": 0.0,
      "extreme_values": []
    },
    "energy": {
      "count": 0,
      "percentage": 0.0,
      "negative_values": 0,
      "extreme_high_values": 0
    }
  },
  "data_freshness": {
    "latest_date": "2025-09-05T00:00:00",
    "oldest_date": "2025-09-03T00:00:00",
    "hours_since_latest": 102.55,
    "is_stale": true,
    "freshness_threshold_hours": 24,
    "date_range_days": 2
  },
  "summary_stats": {
    "lat": {
      "count": 15.0,
      "mean": 38.68118,
      "std": 6.56232855527888,
      "min": 29.7604,
      "25%": 33.4484,
      "50%": 40.7128,
      "75%": 41.8781,
      "max": 47.6062
    },
    "lon": {
      "count": 15.0,
      "mean": -98.28234,
      "std": 17.80790969793238,
      "min": -122.3321,
      "25%": -112.074,
      "50%": -95.3698,
      "75%": -87.6298,
      "max": -74.006
    },
    "temp_max_f": {
      "count": 15.0,
      "mean": 47.30666666666668,
      "std": 2.2673038320142864,
      "min": 43.9,
      "25%": 45.9,
      "50%": 46.8,
      "75%": 49.5,
      "max": 51.1
    },
    "temp_min_f": {
      "count": 15.0,
      "mean": 43.773333333333326,
      "std": 1.906555108291492,
      "min": 40.6,
      "25%": 42.4,
      "50%": 43.5,
      "75%": 45.5,
      "max": 46.6
    },
    "temp_avg_f": {
      "count": 15.0,
      "mean": 45.54,
      "std": 2.0580156878480222,
      "min": 42.25,
      "25%": 44.224999999999994,
      "50%": 44.85,
      "75%": 47.5,
      "max": 48.55
    },
    "energy_consumption_mwh": {
      "count": 15.0,
      "mean": 873926.9333333333,
      "std": 903603.320851536,
      "min": 23916.0,
      "25%": 128580.0,
      "50%": 416045.0,
      "75%": 1571647.0,
      "max": 2297720.0
    },
    "temp_change_f": {
      "count": 10.0,
      "mean": -0.08500000000000156,
      "std": 0.672908281681504,
      "min": -1.2000000000000028,
      "25%": -0.4625000000000039,
      "50%": -0.02499999999999858,
      "75%": 0.5249999999999986,
      "max": 0.6499999999999915
    },
    "energy_change_mwh": {
      "count": 10.0,
      "mean": 16170.3,
      "std": 30535.264833558518,
      "min": -13199.0,
      "25%": -365.75,
      "50%": 8325.0,
      "75%": 20751.5,
      "max": 93041.0
    },
    "energy_change_pct": {
      "count": 10.0,
      "mean": 0.7369982906183004,
      "std": 4.188631914227666,
      "min": -9.362188080747902,
      "25%": 0.052514741800760434,
      "50%": 1.764485321477749,
      "75%": 3.5007254225868314,
      "max": 4.455287288634646
    }
  }
}