{
  "quality_metrics": {
    "timestamp": "2026-04-25T07:22:24.326143",
    "total_records": 13,
    "missing_values": {
      "by_column": {
        "date": 0,
        "city": 0,
        "state": 0,
        "lat": 0,
        "lon": 0,
        "temp_max_f": 0,
        "temp_min_f": 0,
        "temp_avg_f": 0,
        "day_of_week": 0,
        "is_weekend": 0,
        "temp_range": 0,
        "eia_region": 0,
        "energy_consumption_mwh": 0,
        "temp_change_f": 5,
        "energy_change_mwh": 5,
        "energy_change_pct": 5
      },
      "total_missing": 15,
      "percentage_missing": 115.38461538461537
    },
    "outliers": {
      "temperature": {
        "count": 0,
        "percentage": 0.0,
        "extreme_values": []
      },
      "energy": {
        "count": 0,
        "percentage": 0.0,
        "negative_values": 0,
        "extreme_high_values": 0
      }
    },
    "data_freshness": {
      "latest_date": "2026-04-21T00:00:00",
      "oldest_date": "2026-04-19T00:00:00",
      "hours_since_latest": 103.37,
      "is_stale": true,
      "freshness_threshold_hours": 24,
      "date_range_days": 2
    },
    "summary_stats": {
      "lat": {
        "count": 13.0,
        "mean": 39.76991538461539,
        "std": 6.32802234125404,
        "min": 29.7604,
        "25%": 33.4484,
        "50%": 40.7128,
        "75%": 41.8781,
        "max": 47.6062
      },
      "lon": {
        "count": 13.0,
        "mean": -97.4454846153846,
        "std": 18.779212897014887,
        "min": -122.3321,
        "25%": -112.074,
        "50%": -95.3698,
        "75%": -87.6298,
        "max": -74.006
      },
      "temp_max_f": {
        "count": 13.0,
        "mean": 44.223076923076924,
        "std": 2.862735826138417,
        "min": 41.0,
        "25%": 41.7,
        "50%": 44.8,
        "75%": 45.3,
        "max": 49.5
      },
      "temp_min_f": {
        "count": 13.0,
        "mean": 40.70000000000001,
        "std": 2.148255105894084,
        "min": 37.9,
        "25%": 39.0,
        "50%": 41.0,
        "75%": 41.7,
        "max": 44.6
      },
      "temp_avg_f": {
        "count": 13.0,
        "mean": 42.46153846153846,
        "std": 2.4536668007760887,
        "min": 39.75,
        "25%": 40.1,
        "50%": 42.7,
        "75%": 43.35,
        "max": 46.95
      },
      "energy_consumption_mwh": {
        "count": 13.0,
        "mean": 730205.1538461539,
        "std": 808786.4726890576,
        "min": 22415.0,
        "25%": 93564.0,
        "50%": 353927.0,
        "75%": 1113205.0,
        "max": 2069352.0
      },
      "temp_change_f": {
        "count": 8.0,
        "mean": 0.34375,
        "std": 1.371765676574747,
        "min": -1.4500000000000028,
        "25%": -0.23749999999999713,
        "50%": 0.2000000000000028,
        "75%": 0.4249999999999954,
        "max": 3.3500000000000014
      },
      "energy_change_mwh": {
        "count": 8.0,
        "mean": 33263.25,
        "std": 67119.84020019714,
        "min": -6755.0,
        "25%": 948.25,
        "50%": 6310.0,
        "75%": 26624.75,
        "max": 194695.0
      },
      "energy_change_pct": {
        "count": 8.0,
        "mean": 3.4506077341955175,
        "std": 4.275154503627483,
        "min": -1.8728408958583964,
        "25%": -0.0841854067910236,
        "50%": 3.9283320029965596,
        "75%": 6.188290828618226,
        "max": 10.436181406610402
      }
    }
  },
  "correlations": {
    "overall": {
      "correlation_coefficient": -0.3308,
      "r_squared": 0.1094,
      "slope": -109023.482,
      "intercept": 5359509.929,
      "sample_size": 13
    },
    "by_city": {
      "Chicago": {
        "correlation_coefficient": 0.5853,
        "r_squared": 0.3426,
        "slope": 33519.5607,
        "intercept": 622981.0245,
        "sample_size": 3
      },
      "Houston": {
        "correlation_coefficient": 1.0,
        "r_squared": 1.0,
        "slope": 124480.0,
        "intercept": -4307899.0,
        "sample_size": 2
      },
      "New York": {
        "correlation_coefficient": -0.7723,
        "r_squared": 0.5965,
        "slope": -29705.4839,
        "intercept": 1544113.1774,
        "sample_size": 3
      },
      "Phoenix": {
        "correlation_coefficient": 1.0,
        "r_squared": 1.0,
        "slope": 23600.0,
        "intercept": -1010916.0,
        "sample_size": 2
      },
      "Seattle": {
        "correlation_coefficient": 0.2166,
        "r_squared": 0.0469,
        "slope": 214.6445,
        "intercept": 14059.41,
        "sample_size": 3
      }
    }
  },
  "usage_patterns": {
    "by_temperature_range": {
      "mean": {
        "<50\u00b0F": 730205.15
      },
      "median": {
        "<50\u00b0F": 353927.0
      },
      "std": {
        "<50\u00b0F": 808786.47
      },
      "count": {
        "<50\u00b0F": 13
      }
    },
    "by_day_of_week": {
      "mean": {
        "Monday": 731014.8,
        "Sunday": 678179.6,
        "Tuesday": 815565.0
      },
      "median": {
        "Monday": 360682.0,
        "Sunday": 339705.0,
        "Tuesday": 353927.0
      },
      "std": {
        "Monday": 859086.8,
        "Sunday": 782546.99,
        "Tuesday": 1098314.96
      },
      "count": {
        "Monday": 5,
        "Sunday": 5,
        "Tuesday": 3
      }
    },
    "weekend_vs_weekday": {
      "mean": {
        "false": 762721.12,
        "true": 678179.6
      },
      "median": {
        "false": 357304.5,
        "true": 339705.0
      },
      "std": {
        "false": 876528.54,
        "true": 782546.99
      },
      "count": {
        "false": 8,
        "true": 5
      }
    },
    "heatmap_data": {
      "Monday": {
        "<50\u00b0F": 731014.8
      },
      "Sunday": {
        "<50\u00b0F": 678179.6
      },
      "Tuesday": {
        "<50\u00b0F": 815565.0
      }
    }
  },
  "time_series_summary": {
    "date_range": {
      "start": "2026-04-19T00:00:00",
      "end": "2026-04-21T00:00:00",
      "total_days": 2
    },
    "monthly_trends": {
      "temp_avg_f": {
        "2026-04": 42.46
      },
      "energy_consumption_mwh": {
        "2026-04": 730205.15
      }
    }
  }
}